django_reflinks/__init__.py
django_reflinks/admin.py
django_reflinks/middleware.py
django_reflinks/models.py
django_reflinks/settings.py
django_reflinks/urls.py
django_reflinks/views.py
django_reflinks/migrations/0001_initial.py
django_reflinks/migrations/0002_referralhit_http_referer.py
django_reflinks/migrations/__init__.py
django_reflinks-0.5.1.dist-info/METADATA
django_reflinks-0.5.1.dist-info/RECORD
django_reflinks-0.5.1.dist-info/WHEEL
django_reflinks-0.5.1.dist-info/top_level.txt
